accesstrailclient
