Metadata-Version: 1.1
Name: python-accesstrailclient
Version: 0.0.1.dev10
Summary: Client Library for Access Trail API
Home-page: UNKNOWN
Author: UNKNOWN
Author-email: UNKNOWN
License: UNKNOWN
Platform: UNKNOWN
Classifier: Environment :: Other Environment
Classifier: Operating System :: POSIX :: Linux
Classifier: Programming Language :: Python :: 2.7
